nestydict/__init__.py
NestyDict-0.0.6.dist-info/LICENSE
NestyDict-0.0.6.dist-info/METADATA
NestyDict-0.0.6.dist-info/WHEEL
NestyDict-0.0.6.dist-info/top_level.txt
NestyDict-0.0.6.dist-info/RECORD
